{"entities": [{"attributes": [{"name": "attr2", "datatype": "date", "notNULL": "False", "isUNIQUE": "False", "DEFAULT": "", "isPK": "True", "CHECK": ""}, {"name": "attr3", "datatype": "date", "notNULL": "False", "isUNIQUE": "False", "DEFAULT": "", "isPK": "False", "CHECK": ""}], "fds": ["attr2~attr3"], "name": "dummyTable1_0"}, {"attributes": [{"name": "attr1", "datatype": "int(50)", "notNULL": "True", "isUNIQUE": "True", "DEFAULT": "45", "isPK": "True", "CHECK": "attr1>35"}, {"name": "attr2", "datatype": "date", "notNULL": "False", "isUNIQUE": "False", "DEFAULT": "", "isPK": "True", "CHECK": ""}], "fds": [], "name": "dummyTable1"}, {"attributes": [{"name": "attr1", "datatype": "int(50)", "notNULL": "True", "isUNIQUE": "True", "DEFAULT": "45", "isPK": "True", "CHECK": "attr1>35"}], "fds": [], "name": "dummyTable2"}], "relations": [{"to": "dummyTable2", "FK": "attr1", "from": "dummyTable1", "PK": "attr1", "type": "0..N"}, {"to": "dummyTable1_0", "FK": "attr2", "from": "dummyTable1", "PK": "attr2"}]}